<?xml version="1.0" encoding="windows-1252"?>
<?xml-stylesheet type="text/xsl" href="../DiagnosticAddressing.xsl"?>
<Functions xmlns="DiagnosticAddressingSchema.xml">
  <description>
    <Name xml:lang="en">xDE _ Master IV Double Cabin</Name>
    <Name xml:lang="fr" />
  </description>
  <Tool Address="241">
    <XId>2000</XId>
  </Tool>
  <ProtocolList>
    <Protocol Code="6" InitMode="3" MultiPoint="1" Name="DiagOnCAN">
      <Search />
    </Protocol>
    <Protocol Code="9" InitMode="" MultiPoint="" Name="DoIP">
      <Search />
    </Protocol>
    <Protocol Code="8" InitMode="3" MultiPoint="1" Name="DiagOnCANFD">
      <Search />
    </Protocol>
  </ProtocolList>
  <Function Address="0" Name="CAN">
    <baudRate>500000</baudRate>
    <Name xml:lang="en">Primary CAN network</Name>
    <Name xml:lang="fr">Réseau CAN primaire</Name>
  </Function>
  <Function Address="255" Name="CAN2">
    <baudRate>500000</baudRate>
    <Name xml:lang="en">Secondary CAN network</Name>
    <Name xml:lang="fr">Réseau CAN secondaire</Name>
  </Function>
  <Function Address="4" Name="EPS">
    <Name xml:lang="en">Electric Power Steering</Name>
    <Name xml:lang="fr">Direction assistee</Name>
    <XId>1858</XId>
    <RId>1890</RId>
    <ProtocolList>
      <Protocol Code="6" InitMode="3" MultiPoint="1" Name="DiagOnCAN">
        <Address Present="1" Extended="0" Xid="742" Rid="762" />
        <LogicalAddress>1004</LogicalAddress>
        <Search />
      </Protocol>
    </ProtocolList>
  </Function>
  <Function Address="89" Name="MIU">
    <Name xml:lang="en">Multimedia Interface Unit</Name>
    <Name xml:lang="fr">Interface Multimedia</Name>
    <XId>1812</XId>
    <RId>1844</RId>
    <ProtocolList>
      <Protocol Code="6" InitMode="3" MultiPoint="1" Name="DiagOnCAN">
        <Address Present="1" Extended="0" Xid="714" Rid="734" />
        <LogicalAddress>1059</LogicalAddress>
        <Search />
      </Protocol>
    </ProtocolList>
  </Function>
  <Function Address="119" Name="DCM Renault">
    <Name xml:lang="en">Data Communication Module</Name>
    <Name xml:lang="fr">Module telematique de communication</Name>
    <XId>1994</XId>
    <RId>2010</RId>
    <ProtocolList>
      <Protocol Code="9" InitMode="" MultiPoint="" Name="DoIP">
        <LogicalAddress>0077</LogicalAddress>
        <Search />
      </Protocol>
      <Protocol Code="6" InitMode="3" MultiPoint="1" Name="DiagOnCAN">
        <Address Present="1" Extended="0" Xid="7CA" Rid="7DA" />
        <LogicalAddress>1077</LogicalAddress>
        <Search />
      </Protocol>
    </ProtocolList>
  </Function>
  <Function Address="45" Name="ABS-VDC_29b">
    <Name xml:lang="en">ABS-VDC-EBAM_29b</Name>
    <Name xml:lang="fr">ABS-VDC-EBAM_29b</Name>
    <XId>-1730531855</XId>
    <RId>-1730481875</RId>
    <ProtocolList>
      <Protocol Code="8" InitMode="3" MultiPoint="1" Name="DiagOnCANFD">
        <Address Present="0" Extended="0" Xid="740" Rid="760" />
        <Address Present="1" Extended="1" Xid="18DA2DF1" Rid="18DAF12D" />
        <LogicalAddress>102D</LogicalAddress>
        <Search />
      </Protocol>
    </ProtocolList>
  </Function>
  <Function Address="77" Name="SCU">
    <Name xml:lang="en">Shift By Wire</Name>
    <Name xml:lang="fr">Commande Boite Electrique</Name>
    <XId>1949</XId>
    <RId>1981</RId>
    <ProtocolList>
      <Protocol Code="6" InitMode="3" MultiPoint="1" Name="DiagOnCAN">
        <Address Present="1" Extended="0" Xid="79D" Rid="7BD" />
        <LogicalAddress>104D</LogicalAddress>
        <Search />
      </Protocol>
    </ProtocolList>
  </Function>
  <Function Address="151" Name="PLC-PLGW">
    <Name xml:lang="en">Power Line connection- Power Line GateWay</Name>
    <Name xml:lang="fr">Power Line connection- Power Line GateWay</Name>
    <XId>2008</XId>
    <RId>1992</RId>
    <ProtocolList>
      <Protocol Code="6" InitMode="3" MultiPoint="1" Name="DiagOnCAN">
        <Address Present="1" Extended="0" Xid="7D8" Rid="7C8" />
        <LogicalAddress>1097</LogicalAddress>
        <Search />
      </Protocol>
    </ProtocolList>
  </Function>
  <Function Address="58" Name="CAN Adapter - BAC">
    <Name xml:lang="en">Network CAN Adapter</Name>
    <Name xml:lang="fr">Adaptateur reseau CAN</Name>
    <XId>2006</XId>
    <RId>2002</RId>
    <ProtocolList>
      <Protocol Code="6" InitMode="3" MultiPoint="1" Name="DiagOnCAN">
        <Address Present="1" Extended="0" Xid="7D6" Rid="7D2" />
        <LogicalAddress>103A</LogicalAddress>
        <Search />
      </Protocol>
    </ProtocolList>
  </Function>
  <Function Address="88" Name="Navigation-UCC-ITM">
    <Name xml:lang="en">Navigation-UCC-ITM</Name>
    <Name xml:lang="fr">Navigation-UCC-ITM</Name>
    <XId>1863</XId>
    <RId>1895</RId>
    <ProtocolList>
      <Protocol Code="9" InitMode="" MultiPoint="" Name="DoIP">
        <LogicalAddress>0058</LogicalAddress>
        <Search />
      </Protocol>
    </ProtocolList>
  </Function>
  <Function Address="171" Name="BLE VK">
    <Name xml:lang="en">Blue tooth ECU Virtual Key</Name>
    <Name xml:lang="fr">Blue tooth ECU Virtual Key</Name>
    <XId>-1730499598</XId>
    <RId>-1730481493</RId>
    <ProtocolList>
      <Protocol Code="6" InitMode="3" MultiPoint="1" Name="DiagOnCAN">
        <Address Present="1" Extended="1" Xid="18DAABF2" Rid="18DAF2AB" />
        <LogicalAddress>10AB</LogicalAddress>
        <Search />
      </Protocol>
    </ProtocolList>
  </Function>
  <Function Address="222" Name="BCB-OBC_29b">
    <Name xml:lang="en">Battery Charger Block_29bits</Name>
    <Name xml:lang="fr">Module Chargeur Batterie_29bits</Name>
    <XId>-1730486543</XId>
    <RId>-1730481698</RId>
    <ProtocolList>
      <Protocol Code="6" InitMode="3" MultiPoint="1" Name="DiagOnCAN">
        <Address Present="0" Extended="0" Xid="792" Rid="793" />
        <Address Present="1" Extended="1" Xid="18DADEF1" Rid="18DAF1DE" />
        <LogicalAddress>10DE</LogicalAddress>
        <Search />
      </Protocol>
    </ProtocolList>
  </Function>
  <Function Address="225" Name="UDM_29b">
    <Name xml:lang="en">Urea dosing Control Module_29bits</Name>
    <Name xml:lang="fr">Module de controle d'uree_29bits</Name>
    <XId>-1730485775</XId>
    <RId>-1730481695</RId>
    <ProtocolList>
      <Protocol Code="6" InitMode="3" MultiPoint="1" Name="DiagOnCAN">
        <Address Present="0" Extended="0" Xid="7E6" Rid="7EE" />
        <Address Present="1" Extended="1" Xid="18DAE1F1" Rid="18DAF1E1" />
        <LogicalAddress>10E1</LogicalAddress>
        <Search />
      </Protocol>
    </ProtocolList>
  </Function>
  <Function Address="19" Name="Audio">
    <Name xml:lang="en">Audio Unit</Name>
    <Name xml:lang="fr">Radio</Name>
    <XId>1810</XId>
    <RId>1842</RId>
    <ProtocolList>
      <Protocol Code="6" InitMode="3" MultiPoint="1" Name="DiagOnCAN">
        <Address Present="1" Extended="0" Xid="712" Rid="732" />
        <LogicalAddress>1013</LogicalAddress>
        <Search />
      </Protocol>
    </ProtocolList>
  </Function>
  <Function Address="37" Name="IDM-CDM">
    <Name xml:lang="en">Integrated Dynamics Control Module</Name>
    <Name xml:lang="fr">Integrated Dynamics Control Module</Name>
    <XId>1804</XId>
    <RId>1792</RId>
    <ProtocolList>
      <Protocol Code="8" InitMode="3" MultiPoint="1" Name="DiagOnCANFD">
        <Address Present="1" Extended="0" Xid="70C" Rid="700" />
        <LogicalAddress>1025</LogicalAddress>
        <Search />
      </Protocol>
    </ProtocolList>
  </Function>
  <Function Address="81" Name="TDB">
    <Name xml:lang="en">Meter Cluster</Name>
    <Name xml:lang="fr">Tableau de bord</Name>
    <XId>1859</XId>
    <RId>1891</RId>
    <ProtocolList>
      <Protocol Code="6" InitMode="3" MultiPoint="1" Name="DiagOnCAN">
        <Address Present="1" Extended="0" Xid="743" Rid="763" />
        <LogicalAddress>1051</LogicalAddress>
        <Search />
      </Protocol>
    </ProtocolList>
  </Function>
  <Function Address="98" Name="FCAM">
    <Name xml:lang="en">Front camera</Name>
    <Name xml:lang="fr">Camera frontale</Name>
    <XId>2012</XId>
    <RId>2013</RId>
    <ProtocolList>
      <Protocol Code="8" InitMode="3" MultiPoint="1" Name="DiagOnCANFD">
        <Address Present="1" Extended="0" Xid="7DC" Rid="7DD" />
        <LogicalAddress>1062</LogicalAddress>
        <Search />
      </Protocol>
    </ProtocolList>
  </Function>
  <Function Address="99" Name="SOW Rear Left">
    <Name xml:lang="en">Side Obstacle Warning Rear Left</Name>
    <Name xml:lang="fr">Side Obstacle Warning Rear Left</Name>
    <XId>1853</XId>
    <RId>1854</RId>
    <ProtocolList>
      <Protocol Code="8" InitMode="3" MultiPoint="1" Name="DiagOnCANFD">
        <Address Present="1" Extended="0" Xid="73D" Rid="73E" />
        <LogicalAddress>1063</LogicalAddress>
        <Search />
      </Protocol>
    </ProtocolList>
  </Function>
  <Function Address="100" Name="SOW Rear Right">
    <Name xml:lang="en">Side Obstacle Warning Rear Right</Name>
    <Name xml:lang="fr">Side Obstacle Warning Rear Right</Name>
    <XId>2004</XId>
    <RId>2005</RId>
    <ProtocolList>
      <Protocol Code="8" InitMode="3" MultiPoint="1" Name="DiagOnCANFD">
        <Address Present="1" Extended="0" Xid="7D4" Rid="7D5" />
        <LogicalAddress>1064</LogicalAddress>
        <Search />
      </Protocol>
    </ProtocolList>
  </Function>
  <Function Address="130" Name="WCGS">
    <Name xml:lang="en">Wireless Charger Smartphone</Name>
    <Name xml:lang="fr">Wireless Charger Smartphone</Name>
    <XId>1962</XId>
    <RId>1965</RId>
    <ProtocolList>
      <Protocol Code="6" InitMode="3" MultiPoint="1" Name="DiagOnCAN">
        <Address Present="1" Extended="0" Xid="7AA" Rid="7AD" />
        <LogicalAddress>1082</LogicalAddress>
        <Search />
      </Protocol>
    </ProtocolList>
  </Function>
  <Function Address="192" Name="HFM">
    <Name xml:lang="en">Hand Free Module</Name>
    <Name xml:lang="fr">Module Mains Libres</Name>
    <XId>1945</XId>
    <RId>1977</RId>
    <ProtocolList>
      <Protocol Code="6" InitMode="3" MultiPoint="1" Name="DiagOnCAN">
        <Address Present="1" Extended="0" Xid="799" Rid="7B9" />
        <LogicalAddress>10C0</LogicalAddress>
        <Search />
      </Protocol>
    </ProtocolList>
  </Function>
  <Function Address="218" Name="(H) EVC-HCM-VCM_29b">
    <Name xml:lang="en">Vehicle Control Module_29bits</Name>
    <Name xml:lang="fr">Vehicle Control Module_29bits</Name>
    <XId>-1730487567</XId>
    <RId>-1730481702</RId>
    <ProtocolList>
      <Protocol Code="8" InitMode="3" MultiPoint="1" Name="DiagOnCANFD">
        <Address Present="0" Extended="0" Xid="7E4" Rid="7EC" />
        <Address Present="1" Extended="1" Xid="18DADAF1" Rid="18DAF1DA" />
        <LogicalAddress>10DA</LogicalAddress>
        <Search />
      </Protocol>
    </ProtocolList>
  </Function>
</Functions>