{
"autoidents": [
	{
	"diagversion": "0",
	"supplier": "000",
	"soft": "0003",
	"version": "0000"
	},
	{
	"diagversion": "0",
	"supplier": "000",
	"soft": "0004",
	"version": "0000"
	},
	{
	"diagversion": "0",
	"supplier": "000",
	"soft": "0005",
	"version": "0000"
	},
	{
	"diagversion": "0",
	"supplier": "000",
	"soft": "0006",
	"version": "0000"
	}
],
"ecuname": "X65 X35 Climatisation R\u00e9gul\u00e9e",
"obd": {
	"protocol": "KWP2000",
	"fastinit": true,
	"funcaddr": "29",
	"funcname": "Climatisation",
	"kw1": "F1",
	"kw2": "29"
},
"data": {
	"Code ITG Fournisseur": {
	"bitscount": 32,
	"byte": true,
	"bytescount": 4,
	"comment": "cod\u00e9 sur 4 octets 00 00 04 02 ==> 42"
	},
	"Configuration du syst\u00e8me": {
	"scaled": true,
	"format": "bin",
	"comment": "Configuration du syst\u00e8me"
	},
	"Echo Service": {
	"scaled": true
	},
	"Effacer toutes les Pannes": {
	"scaled": true
	},
	"N\u00b0 calibration": {
	"bitscount": 16,
	"byte": true,
	"bytescount": 2,
	"comment": "Num\u00e9ro de calibration"
	},
	"N\u00b0 version": {
	"bitscount": 16,
	"byte": true,
	"bytescount": 2,
	"comment": "Num\u00e9ro de version"
	},
	"Pannes m\u00e9moris\u00e9es 1": {
	"scaled": true,
	"format": "bin",
	"comment": "Pannes m\u00e9moris\u00e9es 1"
	},
	"Pannes m\u00e9moris\u00e9es 2": {
	"scaled": true,
	"format": "bin",
	"comment": "Pannes m\u00e9moris\u00e9es 2"
	},
	"Pannes pr\u00e9sentes 1": {
	"scaled": true,
	"format": "bin",
	"comment": "Pannes pr\u00e9sentes 1"
	},
	"Pannes pr\u00e9sentes 2": {
	"scaled": true,
	"format": "bin",
	"comment": "Pannes pr\u00e9sentes 2"
	},
	"Position du volet de distribution": {
	"scaled": true,
	"unit": "%",
	"comment": "Position du volet de distribution"
	},
	"Position du volet de mixage": {
	"scaled": true,
	"unit": "%",
	"comment": "Position du volet de mixage"
	},
	"R\u00e9f\u00e9rence RENAULT": {
	"bitscount": 40,
	"byte": true,
	"bytescount": 5,
	"comment": "R\u00e9f\u00e9rence RENAULT"
	},
	"Sens de pilotage Distrib": {
	"lists": {
		"0": "Vers A\u00e9rateur",
		"240": "Vers D\u00e9gi"
	}
	},
	"Sens de pilotage Mixage": {
	"lists": {
		"0": "Vers tout froid",
		"240": "Vers tout chaud"
	}
	},
	"Sens de pilotage Recy": {
	"lists": {
		"0": "Vers Air Ext.",
		"240": "Vers RECY"
	}
	},
	"Service": {
	"byte": true
	},
	"Sortie \u00e0 arreter": {
	"lists": {
		"128": "GMV habitacle",
		"129": "AC_CYCLE",
		"132": "Moteur de recyclage",
		"133": "T\u00e9moins Fct",
		"134": "Moteur de distribution",
		"135": "Moteur de mixage"
	},
	"comment": "Sortie \u00e0 arr\u00eater"
	},
	"Sortie \u00e0 piloter": {
	"lists": {
		"128": "GMV habitacle",
		"129": "AC_CYCLE",
		"132": "Moteur de recyclage",
		"133": "T\u00e9moins Fct",
		"134": "Moteur de distribution",
		"135": "Moteur de mixage"
	},
	"comment": "Sortie \u00e0 piloter"
	},
	"Sortie \u00e0 surveiller": {
	"lists": {
		"128": "GMV habitacle",
		"129": "AC_CYCLE",
		"132": "Moteur de recyclage",
		"133": "T\u00e9moins Fct",
		"134": "Moteur de distribution",
		"135": "Moteur de mixage"
	},
	"comment": "Sortie \u00e0 surveiller"
	},
	"Status de la sortie": {
	"lists": {
		"0": "- rien - ",
		"1": "pilotage EN COURS",
		"2": "pilotage TERMINE",
		"241": "pilotage SENS INVERSE EN COURS"
	},
	"comment": "Status de la sortie"
	},
	"Temp\u00e9rature Air Souffl\u00e9 sortie radiateur": {
	"bitscount": 7,
	"scaled": true,
	"step": 0.5,
	"format": "#0.0",
	"unit": "\u00b0C",
	"comment": "Temp\u00e9rature d' Air souffl\u00e9 1"
	},
	"Temp\u00e9rature ext\u00e9rieure": {
	"bitscount": 7,
	"scaled": true,
	"step": 0.5,
	"format": "#0.0",
	"unit": "\u00b0C"
	},
	"Temp\u00e9rature Int\u00e9rieure": {
	"bitscount": 7,
	"scaled": true,
	"step": 0.5,
	"format": "#0.0",
	"unit": "\u00b0C",
	"comment": "Temp\u00e9rature Int\u00e9rieur"
	},
	"Tension alimentation du calculateur": {
	"scaled": true,
	"step": 0.1,
	"unit": "V",
	"comment": "Tension d' alimentation du calculateur"
	},
	"Version climatisation": {
	"lists": {
		"0": "BAC",
		"6": "X65 R\u00e9gul\u00e9e"
	},
	"comment": "Version climatisation : R\u00e9gul\u00e9e"
	},
	"Vitesse moto ventillateur": {
	"scaled": true,
	"unit": "%",
	"comment": "Vitesse moto ventilateur"
	},
	"Panne m\u00e9moris\u00e9e CC sonde Temp. Air Souffl\u00e9 sortie radiateur": {
	"bitscount": 1,
	"lists": {
		"0": "NON",
		"1": "OUI"
	},
	"comment": "Panne m\u00e9moris\u00e9e CC sonde Temp. Air Souffl\u00e9 Pieds"
	},
	"Panne m\u00e9moris\u00e9e CC sonde Temp. int\u00e9rieur": {
	"bitscount": 1,
	"lists": {
		"0": "NON",
		"1": "OUI"
	},
	"comment": "Panne m\u00e9moris\u00e9e CC sonde Temp. Int\u00e9rieure"
	},
	"Panne m\u00e9moris\u00e9e CO sonde Temp. Air Souffl\u00e9 sortie radiateur": {
	"bitscount": 1,
	"lists": {
		"0": "NON",
		"1": "OUI"
	},
	"comment": "Panne m\u00e9moris\u00e9e CO sonde Temp. Air Souffl\u00e9 Pieds"
	},
	"Panne m\u00e9moris\u00e9e CO sonde Temp. int\u00e9rieur": {
	"bitscount": 1,
	"lists": {
		"0": "NON",
		"1": "OUI"
	},
	"comment": "Panne m\u00e9moris\u00e9e CO sonde Temp. Int\u00e9rieure"
	},
	"Panne pr\u00e9sente CC sonde Temp. Air Souffl\u00e9 sortie radiateur": {
	"bitscount": 1,
	"lists": {
		"0": "NON",
		"1": "OUI"
	},
	"comment": "Panne pr\u00e9sente CC sonde Temp. Air Souffl\u00e9 Pieds"
	},
	"Panne pr\u00e9sente CC sonde Temp. int\u00e9rieur": {
	"bitscount": 1,
	"lists": {
		"0": "NON",
		"1": "OUI"
	},
	"comment": "Panne pr\u00e9sente CC sonde Temp. Int\u00e9rieure"
	},
	"Panne pr\u00e9sente CO retour vitesse": {
	"bitscount": 1,
	"lists": {
		"0": "NON",
		"1": "OUI"
	}
	},
	"Panne pr\u00e9sente CO sonde Temp. Air Souffl\u00e9 sortie radiateur": {
	"bitscount": 1,
	"lists": {
		"0": "NON",
		"1": "OUI"
	},
	"comment": "Panne pr\u00e9sente CO sonde Temp. Air Souffl\u00e9 Pieds"
	},
	"Panne pr\u00e9sente CO sonde Temp. int\u00e9rieur": {
	"bitscount": 1,
	"lists": {
		"0": "NON",
		"1": "OUI"
	},
	"comment": "Panne pr\u00e9sente CO sonde Temp. Int\u00e9rieure"
	},
	"Panne pr\u00e9sente EEPROM": {
	"bitscount": 1,
	"lists": {
		"0": "NON",
		"1": "OUI"
	},
	"comment": "Panne pr\u00e9sente EEPROM"
	},
	"Panne pr\u00e9sente moteur de distribution": {
	"bitscount": 1,
	"lists": {
		"0": "NON",
		"1": "OUI"
	},
	"comment": "Panne pr\u00e9sente moteur de distrubution"
	},
	"Panne pr\u00e9sente moteur de mixage": {
	"bitscount": 1,
	"lists": {
		"0": "NON",
		"1": "OUI"
	},
	"comment": "Panne pr\u00e9sente moteur de mixage"
	},
	"Panne pr\u00e9sente moteur de recyclage": {
	"bitscount": 1,
	"lists": {
		"0": "NON",
		"1": "OUI"
	},
	"comment": "Panne pr\u00e9sente moteur de recyclage"
	},
	"Signe Temp\u00e9rature Ext\u00e9rieure": {
	"bitscount": 1,
	"lists": {
		"0": "+",
		"1": "-"
	},
	"comment": "Temp\u00e9rature Ext\u00e9rieur"
	},
	"Signe Temp\u00e9rature Int\u00e9rieure": {
	"bitscount": 1,
	"lists": {
		"0": "+",
		"1": "-"
	}
	},
	"Panne m\u00e9moris\u00e9e CO retour vitesse": {
	"bitscount": 1,
	"lists": {
		"0": "NON",
		"1": "OUI"
	}
	},
	"Panne m\u00e9moris\u00e9e EEPROM": {
	"bitscount": 1,
	"lists": {
		"0": "NON",
		"1": "OUI"
	},
	"comment": "Panne m\u00e9moris\u00e9e EEPROM"
	},
	"Panne m\u00e9moris\u00e9e moteur de distribution": {
	"bitscount": 1,
	"lists": {
		"0": "NON",
		"1": "OUI"
	},
	"comment": "Panne m\u00e9moris\u00e9e moteur de distrubution"
	},
	"Panne m\u00e9moris\u00e9e moteur de mixage": {
	"bitscount": 1,
	"lists": {
		"0": "NON",
		"1": "OUI"
	},
	"comment": "Panne m\u00e9moris\u00e9e moteur de mixage"
	},
	"Panne m\u00e9moris\u00e9e moteur de recyclage": {
	"bitscount": 1,
	"lists": {
		"0": "NON",
		"1": "OUI"
	},
	"comment": "Panne m\u00e9moris\u00e9e moteur de recyclage"
	},
	"Pr\u00e9sence +12V ACC": {
	"bitscount": 1,
	"lists": {
		"0": "OFF",
		"1": "ON"
	},
	"comment": "Pr\u00e9sence +12 V ACC"
	},
	"Pr\u00e9sence du +12 LANT": {
	"bitscount": 1,
	"lists": {
		"0": "OFF",
		"1": "ON"
	},
	"comment": "Pr\u00e9sence du +12 LANT"
	},
	"N\u00b0 hardware": {
	"bitscount": 40,
	"byte": true,
	"bytescount": 5,
	"comment": "Num\u00e9ro de Hardware"
	},
	"Signe TASsortie radiateur": {
	"bitscount": 1,
	"lists": {
		"0": "+",
		"1": "-"
	}
	},
	"Commande recy": {
	"bitscount": 1,
	"lists": {
		"0": "Air ext",
		"1": "Recy"
	},
	"comment": "Commande recy"
	},
	"Demande AC": {
	"bitscount": 1,
	"lists": {
		"0": "OFF",
		"1": "ON"
	},
	"comment": "demande AC"
	},
	"Demande RECY": {
	"bitscount": 1,
	"lists": {
		"0": "OFF",
		"1": "ON"
	},
	"comment": "demande RECY"
	},
	"N\u00b0 du logiciel": {
	"bitscount": 16,
	"byte": true,
	"bytescount": 2,
	"comment": "Num\u00e9ro du logiciel"
	},
	"SessionName": {
	"lists": {
		"129": "DefaultSession",
		"160": "EngineeringSession",
		"192": "AfterSaleSession"
	}
	}
},
"requests": [
	{
	"minbytes": 1,
	"manualsend": true,
	"sentbytes": "308000",
	"name": "00-D\u00e9butPilotage des Sorties",
	"deny_sds": [],
	"sendbyte_dataitems": {
		"Sortie \u00e0 piloter": {
		"firstbyte": 2,
		"ref": true
		}
	}
	},
	{
	"minbytes": 1,
	"manualsend": true,
	"sentbytes": "308000",
	"name": "01-D\u00e9butPilotage GMV habitacle",
	"deny_sds": []
	},
	{
	"minbytes": 1,
	"manualsend": true,
	"sentbytes": "308100",
	"name": "02-D\u00e9butPilotage AC_CYCLE",
	"deny_sds": []
	},
	{
	"minbytes": 1,
	"manualsend": true,
	"sentbytes": "308400",
	"name": "05-DebutPilotage Moteur Recyclage",
	"deny_sds": [],
	"sendbyte_dataitems": {
		"Sens de pilotage Recy": {
		"firstbyte": 3,
		"ref": true
		}
	}
	},
	{
	"minbytes": 1,
	"manualsend": true,
	"sentbytes": "308500",
	"name": "06-DebutPilotageT\u00e9moins de FCT",
	"deny_sds": []
	},
	{
	"minbytes": 1,
	"manualsend": true,
	"sentbytes": "308600",
	"name": "07-DebutPilotage Moteur distribution",
	"deny_sds": [],
	"sendbyte_dataitems": {
		"Sens de pilotage Distrib": {
		"firstbyte": 3,
		"ref": true
		}
	}
	},
	{
	"minbytes": 1,
	"sentbytes": "308700",
	"name": "08-DebutPilotage Moteur mixage",
	"deny_sds": [],
	"sendbyte_dataitems": {
		"Sens de pilotage Mixage": {
		"firstbyte": 3,
		"ref": true
		}
	}
	},
	{
	"minbytes": 1,
	"manualsend": true,
	"sentbytes": "308011",
	"name": "10-ArretPilotageDesSorties",
	"deny_sds": [],
	"sendbyte_dataitems": {
		"Sortie \u00e0 arreter": {
		"firstbyte": 2,
		"ref": true
		}
	}
	},
	{
	"minbytes": 1,
	"manualsend": true,
	"sentbytes": "308011",
	"name": "11-ArretPilotageGMV habitacle",
	"deny_sds": []
	},
	{
	"minbytes": 1,
	"manualsend": true,
	"sentbytes": "308111",
	"name": "12-ArretPilotageAC_CYCLE",
	"deny_sds": []
	},
	{
	"minbytes": 1,
	"manualsend": true,
	"sentbytes": "308411",
	"name": "15-ArretPilotageMoteurRecyclage",
	"deny_sds": []
	},
	{
	"minbytes": 1,
	"manualsend": true,
	"sentbytes": "308511",
	"name": "16-ArretPilotage T\u00e9moins de Fct",
	"deny_sds": []
	},
	{
	"minbytes": 1,
	"manualsend": true,
	"sentbytes": "308611",
	"name": "17-ArretPilotage Moteur Distribution",
	"deny_sds": []
	},
	{
	"minbytes": 1,
	"manualsend": true,
	"sentbytes": "308711",
	"name": "18-ArretPilotageMoteur Mixage",
	"deny_sds": []
	},
	{
	"minbytes": 1,
	"manualsend": true,
	"sentbytes": "14FF00",
	"name": "ClearDiagInfo",
	"deny_sds": [],
	"sendbyte_dataitems": {
		"Effacer toutes les Pannes": {
		"firstbyte": 3,
		"ref": true
		}
	}
	},
	{
	"minbytes": 20,
	"sentbytes": "21C0",
	"name": "Diagnostic Syst\u00e8me",
	"deny_sds": [],
	"receivebyte_dataitems": {
		"Panne m\u00e9moris\u00e9e CC sonde Temp. Air Souffl\u00e9 sortie radiateur": {
		"firstbyte": 5,
		"bitoffset": 1,
		"ref": true
		},
		"Panne m\u00e9moris\u00e9e CC sonde Temp. int\u00e9rieur": {
		"firstbyte": 5,
		"bitoffset": 7,
		"ref": true
		},
		"Panne m\u00e9moris\u00e9e CO sonde Temp. Air Souffl\u00e9 sortie radiateur": {
		"firstbyte": 5,
		"ref": true
		},
		"Panne m\u00e9moris\u00e9e CO sonde Temp. int\u00e9rieur": {
		"firstbyte": 5,
		"bitoffset": 6,
		"ref": true
		},
		"Panne pr\u00e9sente CC sonde Temp. Air Souffl\u00e9 sortie radiateur": {
		"firstbyte": 3,
		"bitoffset": 1,
		"ref": true
		},
		"Panne pr\u00e9sente CC sonde Temp. int\u00e9rieur": {
		"firstbyte": 3,
		"bitoffset": 7,
		"ref": true
		},
		"Panne pr\u00e9sente CO retour vitesse": {
		"firstbyte": 4,
		"bitoffset": 6,
		"ref": true
		},
		"Panne pr\u00e9sente CO sonde Temp. Air Souffl\u00e9 sortie radiateur": {
		"firstbyte": 3,
		"ref": true
		},
		"Panne pr\u00e9sente CO sonde Temp. int\u00e9rieur": {
		"firstbyte": 3,
		"bitoffset": 6,
		"ref": true
		},
		"Panne pr\u00e9sente EEPROM": {
		"firstbyte": 4,
		"ref": true
		},
		"Panne pr\u00e9sente moteur de distribution": {
		"firstbyte": 4,
		"bitoffset": 5,
		"ref": true
		},
		"Panne pr\u00e9sente moteur de mixage": {
		"firstbyte": 4,
		"bitoffset": 4,
		"ref": true
		},
		"Panne pr\u00e9sente moteur de recyclage": {
		"firstbyte": 4,
		"bitoffset": 3,
		"ref": true
		},
		"Signe Temp\u00e9rature Ext\u00e9rieure": {
		"firstbyte": 9,
		"ref": true
		},
		"Signe Temp\u00e9rature Int\u00e9rieure": {
		"firstbyte": 8,
		"ref": true
		},
		"Panne m\u00e9moris\u00e9e CO retour vitesse": {
		"firstbyte": 6,
		"bitoffset": 6,
		"ref": true
		},
		"Panne m\u00e9moris\u00e9e EEPROM": {
		"firstbyte": 6,
		"ref": true
		},
		"Panne m\u00e9moris\u00e9e moteur de distribution": {
		"firstbyte": 6,
		"bitoffset": 5,
		"ref": true
		},
		"Panne m\u00e9moris\u00e9e moteur de mixage": {
		"firstbyte": 6,
		"bitoffset": 4,
		"ref": true
		},
		"Panne m\u00e9moris\u00e9e moteur de recyclage": {
		"firstbyte": 6,
		"bitoffset": 3,
		"ref": true
		},
		"Signe TASsortie radiateur": {
		"firstbyte": 12,
		"ref": true
		},
		"Commande recy": {
		"firstbyte": 20,
		"bitoffset": 1,
		"ref": true
		},
		"Demande AC": {
		"firstbyte": 20,
		"bitoffset": 7,
		"ref": true
		},
		"Demande RECY": {
		"firstbyte": 20,
		"bitoffset": 6,
		"ref": true
		},
		"Pannes m\u00e9moris\u00e9es 1": {
		"firstbyte": 5,
		"ref": true
		},
		"Pannes m\u00e9moris\u00e9es 2": {
		"firstbyte": 6,
		"ref": true
		},
		"Pannes pr\u00e9sentes 1": {
		"firstbyte": 3,
		"ref": true
		},
		"Pannes pr\u00e9sentes 2": {
		"firstbyte": 4,
		"ref": true
		},
		"Position du volet de distribution": {
		"firstbyte": 16,
		"ref": true
		},
		"Position du volet de mixage": {
		"firstbyte": 17,
		"ref": true
		},
		"Pr\u00e9sence +12V ACC": {
		"firstbyte": 19,
		"bitoffset": 7,
		"ref": true
		},
		"Pr\u00e9sence du +12 LANT": {
		"firstbyte": 19,
		"bitoffset": 6,
		"ref": true
		},
		"Temp\u00e9rature Air Souffl\u00e9 sortie radiateur": {
		"firstbyte": 12,
		"bitoffset": 1,
		"ref": true
		},
		"Temp\u00e9rature ext\u00e9rieure": {
		"firstbyte": 9,
		"bitoffset": 1,
		"ref": true
		},
		"Temp\u00e9rature Int\u00e9rieure": {
		"firstbyte": 8,
		"bitoffset": 1,
		"ref": true
		},
		"Tension alimentation du calculateur": {
		"firstbyte": 7,
		"ref": true
		},
		"Vitesse moto ventillateur": {
		"firstbyte": 18,
		"ref": true
		}
	}
	},
	{
	"minbytes": 26,
	"sentbytes": "2180",
	"name": "Identification syst\u00e8me",
	"deny_sds": [],
	"receivebyte_dataitems": {
		"Code ITG Fournisseur": {
		"firstbyte": 8,
		"ref": true
		},
		"Configuration du syst\u00e8me": {
		"firstbyte": 23,
		"ref": true
		},
		"N\u00b0 calibration": {
		"firstbyte": 21,
		"ref": true
		},
		"N\u00b0 du logiciel": {
		"firstbyte": 17,
		"ref": true
		},
		"N\u00b0 version": {
		"firstbyte": 19,
		"ref": true
		},
		"N\u00b0 hardware": {
		"firstbyte": 12,
		"ref": true
		},
		"R\u00e9f\u00e9rence RENAULT": {
		"firstbyte": 3,
		"ref": true
		},
		"Version climatisation": {
		"firstbyte": 26,
		"ref": true
		}
	}
	},
	{
	"minbytes": 3,
	"sentbytes": "308001",
	"name": "StatusPilotageDesSorties",
	"deny_sds": [],
	"sendbyte_dataitems": {
		"Sortie \u00e0 surveiller": {
		"firstbyte": 2,
		"ref": true
		}
	},
	"receivebyte_dataitems": {
		"Status de la sortie": {
		"firstbyte": 3
		}
	}
	},
	{
	"minbytes": 1,
	"manualsend": true,
	"sentbytes": "10C0",
	"name": "StartDiagnosticSession",
	"deny_sds": [],
	"sendbyte_dataitems": {
		"SessionName": {
		"firstbyte": 2
		}
	}
	}
],
"devices": [
	{
	"dtc": 0,
	"dtctype": 0,
	"devicedata": {
		"Tension alimentation du calculateur": "0",
		"Pr\u00e9sence +12V ACC": "0",
		"Pr\u00e9sence du +12 LANT": "0"
	},
	"name": "Alimentation"
	},
	{
	"dtc": 0,
	"dtctype": 0,
	"devicedata": {
		"Signe Temp\u00e9rature Int\u00e9rieure": "0",
		"Temp\u00e9rature Int\u00e9rieure": "0",
		"Panne m\u00e9moris\u00e9e CC sonde Temp. int\u00e9rieur": "0",
		"Panne pr\u00e9sente CC sonde Temp. int\u00e9rieur": "0",
		"Panne m\u00e9moris\u00e9e CO sonde Temp. int\u00e9rieur": "0",
		"Panne pr\u00e9sente CO sonde Temp. int\u00e9rieur": "0"
	},
	"name": "Capteur Temp Int."
	},
	{
	"dtc": 0,
	"dtctype": 0,
	"devicedata": {
		"Signe TASsortie radiateur": "0",
		"Temp\u00e9rature Air Souffl\u00e9 sortie radiateur": "0",
		"Panne m\u00e9moris\u00e9e CC sonde Temp. Air Souffl\u00e9 sortie radiateur": "0",
		"Panne pr\u00e9sente CO sonde Temp. Air Souffl\u00e9 sortie radiateur": "0",
		"Panne m\u00e9moris\u00e9e CO sonde Temp. Air Souffl\u00e9 sortie radiateur": "0",
		"Panne pr\u00e9sente CC sonde Temp. Air Souffl\u00e9 sortie radiateur": "0"
	},
	"name": "Capteur Temp. air souffl\u00e9"
	},
	{
	"dtc": 0,
	"dtctype": 3,
	"devicedata": {
		"Vitesse moto ventillateur": "0",
		"Panne pr\u00e9sente CO retour vitesse": "0",
		"Panne m\u00e9moris\u00e9e CO retour vitesse": "0"
	},
	"name": "Consigne Pulseur"
	},
	{
	"dtc": 0,
	"dtctype": 3,
	"devicedata": {
		"Commande recy": "0",
		"Panne m\u00e9moris\u00e9e moteur de recyclage": "0",
		"Panne pr\u00e9sente moteur de recyclage": "0"
	},
	"name": "Position volet Recy"
	},
	{
	"dtc": 0,
	"dtctype": 3,
	"devicedata": {
		"Position du volet de mixage": "0",
		"Panne pr\u00e9sente moteur de mixage": "0",
		"Panne m\u00e9moris\u00e9e moteur de mixage": "0"
	},
	"name": "Position volet mixage"
	},
	{
	"dtc": 0,
	"dtctype": 3,
	"devicedata": {
		"Position du volet de distribution": "0",
		"Panne m\u00e9moris\u00e9e moteur de distribution": "0",
		"Panne pr\u00e9sente moteur de distribution": "0"
	},
	"name": "Position volets distribution"
	},
	{
	"dtc": 0,
	"dtctype": 2,
	"devicedata": {
		"Panne pr\u00e9sente EEPROM": "0",
		"Panne m\u00e9moris\u00e9e EEPROM": "0"
	},
	"name": "Eeprom"
	}
],
"endian": "Big"
}