<?xml version="1.0" encoding="utf-8"?>
<LabelsFile ecuID="" familyName="" protocolID="">
  <Labels>
    <Readable/>
    <Writable/>
    <IOControl/>
    <Snapshot/>
    <Extended/>
    <Fault>
      <Label Name="DF009M" Description="ECU_CALIBRATION_PARAMETER_MEMORY_FAILURE">
        <Requirement Constraints="" Conformity=""/>
        <Variants>
          <VariantLink DDTVariant="CMF1ph2_REPS_V3.3" EVariantName="CMF1ph2_REPS_V3.3">
<DataLink Subname="1" ID_DTC="5608" DTC_FT="44" DDTLink="HEPS_ECU" SN="" Constraints="" Conformity=""/>
<DataLink Subname="2" ID_DTC="5608" DTC_FT="45" DDTLink="HEPS_ECU" SN="" Constraints="" Conformity=""/>
<DataLink Subname="3" ID_DTC="5608" DTC_FT="46" DDTLink="HEPS_ECU" SN="" Constraints="" Conformity=""/>
<DataLink Subname="4" ID_DTC="5608" DTC_FT="49" DDTLink="HEPS_ECU" SN="" Constraints="" Conformity=""/>
<DataLink Subname="5" ID_DTC="5608" DTC_FT="55" DDTLink="HEPS_ECU" SN="" Constraints="" Conformity=""/>
<DataLink Subname="6" ID_DTC="5608" DTC_FT="54" DDTLink="HEPS_ECU" SN="" Constraints="" Conformity=""/>
<DataLink Subname="7" ID_DTC="5608" DTC_FT="96" DDTLink="HEPS_ECU" SN="" Constraints="" Conformity=""/>
<DataLink Subname="8" ID_DTC="5608" DTC_FT="43" DDTLink="HEPS_ECU" SN="" Constraints="" Conformity=""/>
</VariantLink>
        </Variants>
      </Label>
      <Label Name="DF009N" Description="TORQUE_SENSOR_COMPONENT_INTERNAL_FAILURE">
        <Requirement Constraints="" Conformity=""/>
        <Variants>
          <VariantLink DDTVariant="CMF1ph2_REPS_V3.3" EVariantName="CMF1ph2_REPS_V3.3">
<DataLink Subname="1" ID_DTC="5604" DTC_FT="96" DDTLink="EPS_TorqueSensor" SN="" Constraints="" Conformity=""/>
</VariantLink>
        </Variants>
      </Label>
      <Label Name="DF009O" Description="EPS_MOTOR_COMPONENT_INTERNAL_FAILURE">
        <Requirement Constraints="" Conformity=""/>
        <Variants>
          <VariantLink DDTVariant="CMF1ph2_REPS_V3.3" EVariantName="CMF1ph2_REPS_V3.3">
<DataLink Subname="1" ID_DTC="5606" DTC_FT="96" DDTLink="EPS_MOTOR" SN="" Constraints="" Conformity=""/>
</VariantLink>
        </Variants>
      </Label>
      <Label Name="DF009S" Description="LANE_KEEPING_ASSIST_SIGNAL_FAILURE">
        <Requirement Constraints="" Conformity=""/>
        <Variants>
          <VariantLink DDTVariant="CMF1ph2_REPS_V3.3" EVariantName="CMF1ph2_REPS_V3.3">
<DataLink Subname="1" ID_DTC="5620" DTC_FT="86" DDTLink="CAN_LCA K1_Failure" SN="" Constraints="" Conformity=""/>
<DataLink Subname="2" ID_DTC="5620" DTC_FT="82" DDTLink="CAN_LCA K1_Failure" SN="" Constraints="" Conformity=""/>
<DataLink Subname="3" ID_DTC="5620" DTC_FT="83" DDTLink="CAN_LCA K1_Failure" SN="" Constraints="" Conformity=""/>
</VariantLink>
        </Variants>
      </Label>
      <Label Name="DF009T" Description="BCM_CAN_SIGNAL_FAILURE">
        <Requirement Constraints="" Conformity=""/>
        <Variants>
          <VariantLink DDTVariant="CMF1ph2_REPS_V3.3" EVariantName="CMF1ph2_REPS_V3.3">
<DataLink Subname="1" ID_DTC="A4A3" DTC_FT="14" DDTLink="AQSReductorSensor" SN="" Constraints="" Conformity=""/>
<DataLink Subname="2" ID_DTC="A4A3" DTC_FT="12" DDTLink="AQSReductorSensor" SN="" Constraints="" Conformity=""/>
<DataLink Subname="3" ID_DTC="A4A5" DTC_FT="14" DDTLink="AQSOxydantSensor" SN="" Constraints="" Conformity=""/>
<DataLink Subname="4" ID_DTC="A4A5" DTC_FT="12" DDTLink="AQSOxydantSensor" SN="" Constraints="" Conformity=""/>
<DataLink Subname="5" ID_DTC="A4A7" DTC_FT="11" DDTLink="AQSSupply" SN="" Constraints="" Conformity=""/>
<DataLink Subname="6" ID_DTC="A4A7" DTC_FT="12" DDTLink="AQSSupply" SN="" Constraints="" Conformity=""/>
<DataLink Subname="7" ID_DTC="A4A8" DTC_FT="14" DDTLink="AQSPreHeat" SN="" Constraints="" Conformity=""/>
<DataLink Subname="8" ID_DTC="A4A8" DTC_FT="12" DDTLink="AQSPreHeat" SN="" Constraints="" Conformity=""/>
</VariantLink>
        </Variants>
      </Label>
      <Label Name="DF009R" Description="INJECTION_COMMUNICATION_SIGNAL_FAILURE">
        <Requirement Constraints="" Conformity=""/>
        <Variants>
          <VariantLink DDTVariant="CMF1ph2_REPS_V3.3" EVariantName="CMF1ph2_REPS_V3.3">
<DataLink Subname="1" ID_DTC="5623" DTC_FT="87" DDTLink="CAN_StopAuto" SN="" Constraints="" Conformity=""/>
<DataLink Subname="2" ID_DTC="5623" DTC_FT="86" DDTLink="CAN_StopAuto" SN="" Constraints="" Conformity=""/>
</VariantLink>
        </Variants>
      </Label>
      <Label Name="DF009Q" Description="ESP_AND_ABS_COMMUNICATION SIGNAL FAILURE">
        <Requirement Constraints="" Conformity=""/>
        <Variants>
          <VariantLink DDTVariant="CMF1ph2_REPS_V3.3" EVariantName="CMF1ph2_REPS_V3.3">
<DataLink Subname="1" ID_DTC="5632" DTC_FT="83" DDTLink="CAN_SWACorrected" SN="" Constraints="" Conformity=""/>
</VariantLink>
        </Variants>
      </Label>
    </Fault>
  </Labels>
</LabelsFile>
