<?xml version="1.0" encoding="windows-1252"?>
<?xml-stylesheet type="text/xsl" href="../DiagnosticAddressing.xsl"?>
<Functions xmlns="DiagnosticAddressingSchema.xml">
  <description>
    <Name xml:lang="en">PZ1A _ [Leaf]</Name>
    <Name xml:lang="fr" />
  </description>
  <Tool Address="241">
    <XId>2000</XId>
  </Tool>
  <ProtocolList>
    <Protocol Code="6" InitMode="3" MultiPoint="1" Name="DiagOnCAN">
      <Search />
    </Protocol>
  </ProtocolList>
  <Function Address="0" Name="CAN">
    <baudRate>500000</baudRate>
    <Name xml:lang="en">Primary CAN network</Name>
    <Name xml:lang="fr">Réseau CAN primaire</Name>
  </Function>
  <Function Address="255" Name="CAN2">
    <baudRate>500000</baudRate>
    <Name xml:lang="en">Secondary CAN network</Name>
    <Name xml:lang="fr">Réseau CAN secondaire</Name>
  </Function>
  <Function Address="14" Name="Parking Sonar">
    <Name xml:lang="en">Parking Sonar</Name>
    <Name xml:lang="fr">Aide au parking</Name>
    <XId>1870</XId>
    <RId>1902</RId>
    <ProtocolList>
      <Protocol Code="6" InitMode="3" MultiPoint="1" Name="DiagOnCAN">
        <Address Present="1" Extended="0" Xid="74E" Rid="76E" />
        <LogicalAddress>000E</LogicalAddress>
        <Search />
      </Protocol>
    </ProtocolList>
  </Function>
  <Function Address="38" Name="UCH">
    <Name xml:lang="en">Body Control Module</Name>
    <Name xml:lang="fr">Unité de Controle Habitacle</Name>
    <XId>1861</XId>
    <RId>1893</RId>
    <ProtocolList>
      <Protocol Code="6" InitMode="3" MultiPoint="1" Name="DiagOnCAN">
        <Address Present="1" Extended="0" Xid="745" Rid="765" />
        <LogicalAddress>0026</LogicalAddress>
        <Search />
      </Protocol>
    </ProtocolList>
  </Function>
  <Function Address="39" Name="UPC-EMM">
    <Name xml:lang="en">USM</Name>
    <Name xml:lang="fr">UPC</Name>
    <XId>1869</XId>
    <RId>1901</RId>
    <ProtocolList>
      <Protocol Code="6" InitMode="3" MultiPoint="1" Name="DiagOnCAN">
        <Address Present="1" Extended="0" Xid="74D" Rid="76D" />
        <Address Present="0" Extended="1" Xid="18DA42F2" Rid="18DAF242" />
        <LogicalAddress>0027</LogicalAddress>
        <Search />
      </Protocol>
    </ProtocolList>
  </Function>
  <Function Address="41" Name="HVAC">
    <Name xml:lang="en">Climate Control</Name>
    <Name xml:lang="fr">Climatisation</Name>
    <XId>1860</XId>
    <RId>1892</RId>
    <ProtocolList>
      <Protocol Code="6" InitMode="3" MultiPoint="1" Name="DiagOnCAN">
        <Address Present="1" Extended="0" Xid="744" Rid="764" />
        <LogicalAddress>0029</LogicalAddress>
        <Search />
      </Protocol>
    </ProtocolList>
  </Function>
  <Function Address="43" Name="FRRAD">
    <Name xml:lang="en">Laser radar for Adaptive Cruise Control System</Name>
    <Name xml:lang="fr">Laser radar for Adaptive Cruise Control System</Name>
    <XId>1827</XId>
    <RId>1845</RId>
    <ProtocolList>
      <Protocol Code="6" InitMode="3" MultiPoint="1" Name="DiagOnCAN">
        <Address Present="1" Extended="0" Xid="723" Rid="735" />
        <LogicalAddress>002B</LogicalAddress>
        <Search />
      </Protocol>
    </ProtocolList>
  </Function>
  <Function Address="162" Name="SCCM">
    <Name xml:lang="en">Steering ECU</Name>
    <Name xml:lang="fr">Streering ECU</Name>
    <XId>-1730501902</XId>
    <RId>-1730481502</RId>
    <ProtocolList>
      <Protocol Code="6" InitMode="3" MultiPoint="1" Name="DiagOnCAN">
        <Address Present="1" Extended="1" Xid="18DAA2F2" Rid="18DAF2A2" />
        <LogicalAddress>00A2</LogicalAddress>
        <Search />
      </Protocol>
    </ProtocolList>
  </Function>
  <Function Address="167" Name="PBD/PTL">
    <Name xml:lang="en">Power Back Door/Power Trank LID</Name>
    <Name xml:lang="fr">Power Back Door/Power Trank LID</Name>
    <XId>1811</XId>
    <RId>1843</RId>
    <ProtocolList>
      <Protocol Code="6" InitMode="3" MultiPoint="1" Name="DiagOnCAN">
        <Address Present="1" Extended="0" Xid="713" Rid="733" />
        <LogicalAddress>00A7</LogicalAddress>
        <Search />
      </Protocol>
    </ProtocolList>
  </Function>
  <Function Address="192" Name="HFM">
    <Name xml:lang="en">Hand Free Module</Name>
    <Name xml:lang="fr">Module Mains Libres</Name>
    <XId>1945</XId>
    <RId>1977</RId>
    <ProtocolList>
      <Protocol Code="6" InitMode="3" MultiPoint="1" Name="DiagOnCAN">
        <Address Present="1" Extended="0" Xid="799" Rid="7B9" />
        <LogicalAddress>00C0</LogicalAddress>
        <Search />
      </Protocol>
    </ProtocolList>
  </Function>
  <Function Address="215" Name="CHADeMo">
    <Name xml:lang="en">Charger/Hevc convertor(CCM/CSCM)</Name>
    <Name xml:lang="fr">Charger/Hevc convertor(CCM/CSCM)</Name>
    <XId>-1730488334</XId>
    <RId>-1730481449</RId>
    <ProtocolList>
      <Protocol Code="6" InitMode="3" MultiPoint="1" Name="DiagOnCAN">
        <Address Present="1" Extended="1" Xid="18DAD7F2" Rid="18DAF2D7" />
        <LogicalAddress>00D7</LogicalAddress>
        <Search />
      </Protocol>
    </ProtocolList>
  </Function>
  <Function Address="218" Name="(H) EVC-HCM-VCM_29b">
    <Name xml:lang="en">Vehicle Control Module_29bits</Name>
    <Name xml:lang="fr">Vehicle Control Module_29bits</Name>
    <XId>-1730487567</XId>
    <RId>-1730481702</RId>
    <ProtocolList>
      <Protocol Code="6" InitMode="3" MultiPoint="1" Name="DiagOnCAN">
        <Address Present="0" Extended="0" Xid="7E4" Rid="7EC" />
        <Address Present="1" Extended="1" Xid="18DADAF1" Rid="18DAF1DA" />
        <LogicalAddress>00DA</LogicalAddress>
        <Search />
      </Protocol>
    </ProtocolList>
  </Function>
  <Function Address="219" Name="LBC (HEV)_29b">
    <Name xml:lang="en">Lithium Battery Controller_29bits</Name>
    <Name xml:lang="fr">Controleur de Batterie Lithium_29bits</Name>
    <XId>-1730487311</XId>
    <RId>-1730481701</RId>
    <ProtocolList>
      <Protocol Code="6" InitMode="3" MultiPoint="1" Name="DiagOnCAN">
        <Address Present="0" Extended="0" Xid="7E5" Rid="7ED" />
        <Address Present="1" Extended="1" Xid="18DADBF1" Rid="18DAF1DB" />
        <LogicalAddress>00DB</LogicalAddress>
        <Search />
      </Protocol>
    </ProtocolList>
  </Function>
  <Function Address="220" Name="LBC2_29b">
    <Name xml:lang="en">Lithium Battery Controller 2_29bits</Name>
    <Name xml:lang="fr">Controleur de Batterie Lithium 2_29bits</Name>
    <XId>-1730487055</XId>
    <RId>-1730481700</RId>
    <ProtocolList>
      <Protocol Code="6" InitMode="3" MultiPoint="1" Name="DiagOnCAN">
        <Address Present="0" Extended="0" Xid="796" Rid="7B6" />
        <Address Present="1" Extended="1" Xid="18DADCF1" Rid="18DAF1DC" />
        <LogicalAddress>00DC</LogicalAddress>
        <Search />
      </Protocol>
    </ProtocolList>
  </Function>
  <Function Address="221" Name="Superviseur-DCDC_29b">
    <Name xml:lang="en">Supervisor-DCDC_29bits</Name>
    <Name xml:lang="fr">Superviseur-DCDC_29bits</Name>
    <XId>-1730486799</XId>
    <RId>-1730481699</RId>
    <ProtocolList>
      <Protocol Code="6" InitMode="3" MultiPoint="1" Name="DiagOnCAN">
        <Address Present="0" Extended="0" Xid="756" Rid="776" />
        <Address Present="1" Extended="1" Xid="18DADDF1" Rid="18DAF1DD" />
        <LogicalAddress>00DD</LogicalAddress>
        <Search />
      </Protocol>
    </ProtocolList>
  </Function>
  <Function Address="223" Name="INV-ME_29b">
    <Name xml:lang="en">INV-ME_29bits</Name>
    <Name xml:lang="fr">INV-ME_29bits</Name>
    <XId>-1730486287</XId>
    <RId>-1730481697</RId>
    <ProtocolList>
      <Protocol Code="6" InitMode="3" MultiPoint="1" Name="DiagOnCAN">
        <Address Present="1" Extended="1" Xid="18DADFF1" Rid="18DAF1DF" />
        <LogicalAddress>00DF</LogicalAddress>
        <Search />
      </Protocol>
    </ProtocolList>
  </Function>
  <Function Address="11" Name="LIB 12V">
    <Name xml:lang="en">LIB</Name>
    <Name xml:lang="fr">LIB</Name>
    <XId>-1730540559</XId>
    <RId>-1730481909</RId>
    <ProtocolList>
      <Protocol Code="6" InitMode="3" MultiPoint="1" Name="DiagOnCAN">
        <Address Present="1" Extended="1" Xid="18DA0BF1" Rid="18DAF10B" />
        <LogicalAddress>000B</LogicalAddress>
        <Search />
      </Protocol>
    </ProtocolList>
  </Function>
  <Function Address="77" Name="SCU">
    <Name xml:lang="en">Shift By Wire</Name>
    <Name xml:lang="fr">Commande Boite Electrique</Name>
    <XId>1949</XId>
    <RId>1981</RId>
    <ProtocolList>
      <Protocol Code="6" InitMode="3" MultiPoint="1" Name="DiagOnCAN">
        <Address Present="1" Extended="0" Xid="79D" Rid="7BD" />
        <LogicalAddress>004D</LogicalAddress>
        <Search />
      </Protocol>
    </ProtocolList>
  </Function>
  <Function Address="222" Name="BCB-OBC_29b">
    <Name xml:lang="en">Battery Charger Block_29bits</Name>
    <Name xml:lang="fr">Module Chargeur Batterie_29bits</Name>
    <XId>-1730486543</XId>
    <RId>-1730481698</RId>
    <ProtocolList>
      <Protocol Code="6" InitMode="3" MultiPoint="1" Name="DiagOnCAN">
        <Address Present="0" Extended="0" Xid="792" Rid="793" />
        <Address Present="1" Extended="1" Xid="18DADEF1" Rid="18DAF1DE" />
        <LogicalAddress>00DE</LogicalAddress>
        <Search />
      </Protocol>
    </ProtocolList>
  </Function>
  <Function Address="152" Name="HVAC 2">
    <Name xml:lang="en">Air Conditioning</Name>
    <Name xml:lang="fr">Air Conditioning</Name>
    <XId>-1730504463</XId>
    <RId>-1730481768</RId>
    <ProtocolList>
      <Protocol Code="6" InitMode="3" MultiPoint="1" Name="DiagOnCAN">
        <Address Present="1" Extended="1" Xid="18DA98F1" Rid="18DAF198" />
        <LogicalAddress>0098</LogicalAddress>
        <Search />
      </Protocol>
    </ProtocolList>
  </Function>
</Functions>